<!DOCTYPE ui:UiBinder SYSTEM "http://dl.google.com/gwt/DTD/xhtml.ent">
<ui:UiBinder xmlns:ui="urn:ui:com.google.gwt.uibinder"
    xmlns:g="urn:import:com.google.gwt.user.client.ui"
    xmlns:my="urn:import:org.dubh.islay.hub.client">
  <ui:style>
  </ui:style>
  <g:HTMLPanel>
    <my:PageHeader ui:field="header" />
    <b>Recent Activities in Buzz:</b>
    <g:SplitLayoutPanel>
    	<g:west size='200'><g:VerticalPanel ui:field="activitiesList" /></g:west>
    	<g:east size='400'><g:Label ui:field="activityStream" /></g:east>
    </g:SplitLayoutPanel>
  </g:HTMLPanel>
</ui:UiBinder> 